flan/__init__.py
flan/__main__.py
flan/export.py
flan/flan.py
flan/flanintegration.py
flan/settings.py
flan/exports/__init__.py
flan/exports/awssqs.py
flan/exports/flanexport.py
flan/exports/fluentd.py
flan/exports/kafka.py
flan/exports/splunk.py
flan/exports/stdout.py
flan/exports/stompmq.py
flan/imports/__init__.py
flan/imports/files.py
flan/imports/flanimport.py
flan/imports/splunk.py
flan/tests/__init__.py
flan/tests/test_flan.py
flan/tests/utils.py
flan-0.0.37.dist-info/LICENSE
flan-0.0.37.dist-info/METADATA
flan-0.0.37.dist-info/WHEEL
flan-0.0.37.dist-info/entry_points.txt
flan-0.0.37.dist-info/top_level.txt
flan-0.0.37.dist-info/RECORD
