Metadata-Version: 2.1
Name: flan
Version: 0.0.37
Summary: Create (very good) fake NCSA Combined Log Format access.log files for testing log-consuming systems like Splunk, ActiveMQ, Amazon MQ, RabbitMQ, Kafka, FluentD, Flume, Pulsar, Nifi...
Home-page: https://github.com/bretlowery/flan
Author: Bret Lowery
Author-email: bret.lowery@gmail.com
License: UNKNOWN
Platform: UNKNOWN
Classifier: Programming Language :: Python :: 3
Classifier: License :: OSI Approved :: MIT License
Classifier: Operating System :: OS Independent
Requires-Dist: python-dateutil (>=2.8.0)
Requires-Dist: ua-parser (>=0.8.0)
Requires-Dist: user-agents (>=2.0)
Requires-Dist: numpy (>=1.16.4.0)
Requires-Dist: service (>=0.6.0)
Requires-Dist: PyYAML (>=5.1.2)
Requires-Dist: boto (>=2.49.0)
Requires-Dist: confluent-kafka (>=1.1.0)
Requires-Dist: fluent-logger (>=0.9.3)
Requires-Dist: pyspark (>=2.4.3)
Requires-Dist: splunk-sdk (>=1.6.6)
Requires-Dist: stomp.py (>=4.1.22)
